agentic_rag/__init__.py
agentic_rag/cli.py
agentic_rag/core/__init__.py
agentic_rag/core/agent.py
agentic_rag/core/memory.py
agentic_rag/core/orchestrator.py
agentic_rag/core/planner.py
agentic_rag/document_processing/__init__.py
agentic_rag/document_processing/chunkers.py
agentic_rag/document_processing/loaders.py
agentic_rag/document_processing/metadata_extractors.py
agentic_rag/document_processing/multimodal_loaders.py
agentic_rag/document_processing/preprocessors.py
agentic_rag/evaluation/__init__.py
agentic_rag/evaluation/benchmarks.py
agentic_rag/evaluation/metrics.py
agentic_rag/graph/__init__.py
agentic_rag/graph/knowledge_graph.py
agentic_rag/llm/__init__.py
agentic_rag/llm/providers.py
agentic_rag/retrieval/__init__.py
agentic_rag/retrieval/rerankers.py
agentic_rag/retrieval/retrievers.py
agentic_rag/retrieval/vector_stores.py
agentic_rag/tools/__init__.py
agentic_rag/tools/base.py
agentic_rag/tools/calculator.py
agentic_rag/tools/code_executor.py
agentic_rag/tools/web_search.py
agentic_rag/utils/__init__.py
agentic_rag/utils/config.py
agentic_rag/utils/exceptions.py
agentic_rag/utils/logging.py
ai_prishtina_agentic_rag-0.1.1.dist-info/licenses/LICENSE
ai_prishtina_agentic_rag-0.1.1.dist-info/METADATA
ai_prishtina_agentic_rag-0.1.1.dist-info/WHEEL
ai_prishtina_agentic_rag-0.1.1.dist-info/top_level.txt
ai_prishtina_agentic_rag-0.1.1.dist-info/RECORD
