Metadata-Version: 2.4
Name: ai-prishtina-agentic-rag
Version: 0.1.1
Summary: A comprehensive, professional-grade agentic Retrieval-Augmented Generation (RAG) library
Home-page: https://github.com/your-org/ai-prishtina-agentic-rag
Author: Alban Maxhuni, PhD
Author-email: "Alban Maxhuni, PhD" <info@albanmaxhuni.com>
License: AGPL-3.0-or-later OR Commercial
Project-URL: Homepage, https://github.com/your-org/ai-prishtina-agentic-rag
Project-URL: Documentation, https://ai-prishtina-agentic-rag.readthedocs.io
Project-URL: Repository, https://github.com/your-org/ai-prishtina-agentic-rag
Project-URL: Issues, https://github.com/your-org/ai-prishtina-agentic-rag/issues
Classifier: Development Status :: 4 - Beta
Classifier: Intended Audience :: Developers
Classifier: License :: OSI Approved :: GNU Affero General Public License v3 or later (AGPLv3+)
Classifier: Programming Language :: Python :: 3
Classifier: Programming Language :: Python :: 3.9
Classifier: Programming Language :: Python :: 3.10
Classifier: Programming Language :: Python :: 3.11
Classifier: Programming Language :: Python :: 3.12
Classifier: Topic :: Scientific/Engineering :: Artificial Intelligence
Classifier: Topic :: Software Development :: Libraries :: Python Modules
Requires-Python: >=3.9
License-File: LICENSE
Requires-Dist: pydantic>=2.0.0
Requires-Dist: typing-extensions>=4.0.0
Requires-Dist: numpy>=1.21.0
Requires-Dist: pandas>=1.3.0
Requires-Dist: openai>=1.0.0
Requires-Dist: anthropic>=0.7.0
Requires-Dist: cohere>=4.0.0
Requires-Dist: transformers>=4.20.0
Requires-Dist: torch>=1.12.0
Requires-Dist: chromadb>=0.4.0
Requires-Dist: pinecone>=3.0.0
Requires-Dist: weaviate-client>=3.15.0
Requires-Dist: faiss-cpu>=1.7.0
Requires-Dist: langchain>=0.1.0
Requires-Dist: pypdf>=3.0.0
Requires-Dist: python-docx>=0.8.11
Requires-Dist: beautifulsoup4>=4.11.0
Requires-Dist: markdown>=3.4.0
Requires-Dist: python-magic>=0.4.27
Requires-Dist: spacy>=3.4.0
Requires-Dist: nltk>=3.8.0
Requires-Dist: sentence-transformers>=2.2.0
Requires-Dist: tiktoken>=0.4.0
Requires-Dist: requests>=2.28.0
Requires-Dist: aiohttp>=3.8.0
Requires-Dist: tenacity>=8.0.0
Requires-Dist: rich>=12.0.0
Requires-Dist: tqdm>=4.64.0
Requires-Dist: pyyaml>=6.0
Requires-Dist: python-dotenv>=0.19.0
Requires-Dist: structlog>=22.0.0
Provides-Extra: dev
Requires-Dist: pytest>=7.0.0; extra == "dev"
Requires-Dist: pytest-asyncio>=0.21.0; extra == "dev"
Requires-Dist: pytest-cov>=4.0.0; extra == "dev"
Requires-Dist: black>=22.0.0; extra == "dev"
Requires-Dist: isort>=5.10.0; extra == "dev"
Requires-Dist: flake8>=5.0.0; extra == "dev"
Requires-Dist: mypy>=1.0.0; extra == "dev"
Requires-Dist: pre-commit>=2.20.0; extra == "dev"
Provides-Extra: docs
Requires-Dist: mkdocs>=1.4.0; extra == "docs"
Requires-Dist: mkdocs-material>=8.5.0; extra == "docs"
Requires-Dist: mkdocstrings[python]>=0.19.0; extra == "docs"
Provides-Extra: all
Requires-Dist: agentic-rag[dev,docs]; extra == "all"
Dynamic: author
Dynamic: home-page
Dynamic: license-file
Dynamic: requires-python
